{
  "$schema": "https://biomejs.dev/schemas/2.4.16/schema.json",
  "vcs": {
    "enabled": true,
    "clientKind": "git",
    "useIgnoreFile": true
  },
  "files": {
    "ignoreUnknown": true,
    "includes": [
      "packages/**/*.{ts,tsx,js,mjs,cjs,json,jsonc}",
      "scripts/**/*.{ts,js}",
      "*.{ts,js,json,jsonc}",
      "!**/dist",
      "!**/dist-bin",
      "!**/dist-tarballs",
      "!**/dist-vendor",
      "!**/.sea-staging",
      "!**/.vendor-build",
      "!**/*.d.ts",
      "!**/eval/data",
      "!**/eval/fixtures",
      "!**/eval/results"
    ]
  },
  "formatter": {
    "enabled": true,
    "indentStyle": "space",
    "indentWidth": 2,
    "lineWidth": 80
  },
  "javascript": {
    "formatter": {
      "quoteStyle": "double",
      "semicolons": "always",
      "trailingCommas": "all"
    }
  },
  "linter": {
    "enabled": true,
    "rules": {
      "recommended": true
    }
  },
  "assist": {
    "enabled": false
  },
  "overrides": [
    {
      "includes": ["**/eval/**"],
      "linter": { "enabled": false }
    }
  ]
}
